confectionary/__init__.py
confectionary/pdf.py
confectionary/report_generation.py
confectionary/text2pdf.py
confectionary/utils.py
confectionary-0.3.data/data/LICENSE
confectionary-0.3.data/data/README.md
confectionary-0.3.data/data/requirements.txt
confectionary-0.3.dist-info/LICENSE
confectionary-0.3.dist-info/METADATA
confectionary-0.3.dist-info/WHEEL
confectionary-0.3.dist-info/top_level.txt
confectionary-0.3.dist-info/RECORD
