Metadata-Version: 2.1
Name: confectionary
Version: 0.3
Summary: A tool to quickly create sweet PDF files from text files.
Home-page: https://github.com/pszemraj/confectionary
Author: Peter Szemraj, Jonathan Lehner
Author-email: szemraj.dev@gmail.com
Classifier: Programming Language :: Python :: 3
Classifier: License :: OSI Approved :: Apache Software License
Classifier: Development Status :: 3 - Alpha
Classifier: Operating System :: OS Independent
Classifier: Natural Language :: English
Classifier: Topic :: Text Processing
Requires-Python: >=3.7
License-File: LICENSE
Requires-Dist: clean-text
Requires-Dist: fpdf2 (==2.5.7)
Requires-Dist: gensim (==4.2.0)
Requires-Dist: natsort
Requires-Dist: nltk (==3.7.0)
Requires-Dist: pandas
Requires-Dist: scikit-learn
Requires-Dist: textsplit (==0.5)
Requires-Dist: tqdm
Requires-Dist: wordninja
Requires-Dist: yake
Requires-Dist: joblib (==1.2.0)
